sduplayground/__init__.py
sduplayground/main.py
sduplayground-0.1.0.dist-info/METADATA
sduplayground-0.1.0.dist-info/WHEEL
sduplayground-0.1.0.dist-info/entry_points.txt
sduplayground-0.1.0.dist-info/top_level.txt
sduplayground-0.1.0.dist-info/RECORD
